binance_historical/__init__.py
binance_historical/binance_historical.py
binance_historical-0.1.1.dist-info/LICENSE
binance_historical-0.1.1.dist-info/METADATA
binance_historical-0.1.1.dist-info/WHEEL
binance_historical-0.1.1.dist-info/top_level.txt
binance_historical-0.1.1.dist-info/RECORD
